rnmd/__init__.py
rnmd/compile_markdown.py
rnmd/configuration_manager.py
rnmd/extract_code.py
rnmd/include-install-rnmd.sh
rnmd/install_markdown.py
rnmd/make_proxy.py
rnmd/proxy-template-py.txt
rnmd/proxy-template.txt
rnmd/rnmd.py
rnmd/runtime.py
rnmd/setup_manager.py
rnmd/config/__init__.py
rnmd/config/defaults.py
rnmd/config/mode_options.py
rnmd/config/mode_printer.py
rnmd/models/__init__.py
rnmd/models/code_block.py
rnmd/models/code_file.py
rnmd/models/code_parser.py
rnmd/models/code_project_parser.py
rnmd/templates/__init__.py
rnmd/templates/proxy-template-py.txt
rnmd/templates/proxy-template.txt
rnmd/util/__init__.py
rnmd/util/extract_document_content.py
rnmd/util/file_tool.py
rnmd/util/web_tool.py
rnmd-1.1.0.dist-info/LICENCE.txt
rnmd-1.1.0.dist-info/METADATA
rnmd-1.1.0.dist-info/WHEEL
rnmd-1.1.0.dist-info/entry_points.txt
rnmd-1.1.0.dist-info/top_level.txt
rnmd-1.1.0.dist-info/RECORD
