Metadata-Version: 2.1
Name: rnmd
Version: 1.1.0
Summary: A runtime for executing interpreted code of markdown files and making them available from anywhere
Home-page: https://github.com/MarkusPeitl/rnmd
Author: Markus Peitl
Author-email: office@markuspeitl.com
License: UNKNOWN
Platform: UNKNOWN
Classifier: Programming Language :: Python :: 3
Classifier: Intended Audience :: Developers
Classifier: License :: OSI Approved :: GNU Lesser General Public License v2 (LGPLv2)
Classifier: Natural Language :: English
Classifier: Topic :: Software Development :: Code Generators
Classifier: Topic :: Software Development :: Documentation
Classifier: Topic :: Text Processing :: Markup :: Markdown
Requires-Python: >=3
Requires-Dist: argparse
Requires-Dist: requests
